googletrans/__init__.py
googletrans/adapters.py
googletrans/cli.py
googletrans/client.py
googletrans/compat.py
googletrans/constants.py
googletrans/gtoken.py
googletrans/models.py
googletrans/urls.py
googletrans/utils.py
py_googletrans_html-2.4.1.dist-info/entry_points.txt
py_googletrans_html-2.4.1.dist-info/LICENSE
py_googletrans_html-2.4.1.dist-info/WHEEL
py_googletrans_html-2.4.1.dist-info/METADATA
py_googletrans_html-2.4.1.dist-info/RECORD
