Metadata-Version: 2.1
Name: py-googletrans-html
Version: 2.4.1
Summary: Free Google Translate API for Python. Translates totally free of charge.
Home-page: https://github.com/KristobalJunta/py-googletrans-html
License: MIT
Keywords: google,translate,translator
Author: SuHun Han
Author-email: ssut@ssut.me
Requires-Python: >=3.6,<4.0
Classifier: Development Status :: 5 - Production/Stable
Classifier: Intended Audience :: Education
Classifier: Intended Audience :: End Users/Desktop
Classifier: License :: Freeware
Classifier: License :: OSI Approved :: MIT License
Classifier: Operating System :: MacOS :: MacOS X
Classifier: Operating System :: Microsoft :: Windows
Classifier: Operating System :: POSIX
Classifier: Programming Language :: Python
Classifier: Programming Language :: Python :: 2.7
Classifier: Programming Language :: Python :: 3
Classifier: Programming Language :: Python :: 3.4
Classifier: Programming Language :: Python :: 3.5
Classifier: Programming Language :: Python :: 3.6
Classifier: Programming Language :: Python :: 3.7
Classifier: Programming Language :: Python :: 3.8
Classifier: Topic :: Education
Provides-Extra: h2
Requires-Dist: coveralls (>=2.0.0,<3.0.0)
Requires-Dist: requests (>=2.23.0,<3.0.0)
Project-URL: Repository, https://github.com/KristobalJunta/py-googletrans-html
